Metadata-Version: 2.1
Name: pydocstring-coverage
Version: 1.0.5
Summary: Utility for examining python source files to ensure proper documentation. Lists missing docstrings, and calculates overall docstring coverage percentage rating
Home-page: https://github.com/danielsuo/docstring-coverage
Author: Hunter McGushion
Author-email: hunter@mcgushion.com
License: MIT
Keywords: docstring coverage documentation audit source code statistics report
Platform: UNKNOWN
Classifier: Programming Language :: Python :: 3
Classifier: License :: OSI Approved :: MIT License
Classifier: Operating System :: OS Independent
Classifier: Topic :: Documentation
Classifier: Topic :: Documentation :: Sphinx
Classifier: Topic :: Software Development
Classifier: Topic :: Software Development :: Documentation
Classifier: Topic :: Software Development :: Libraries :: Python Modules
Classifier: Topic :: Software Development :: Quality Assurance
Classifier: Topic :: Utilities
